{
  "id": 30004,
  "name": "Mesa de Centro",
  "description": "A침ade m치s funciones a tu sala de estar, ya que te permite cambiar f치cilmente de actividad.",
  "cost": 10000,
  "currency": "UYU",
  "soldCount": 37,
  "category": "Muebles",
  "images": [
      "img/px/prod30004_1.jpg",
      "img/px/prod30004_2.jpg",
      "img/px/prod30004_3.jpg"
  ],
  "relatedProducts": [
    {
          "id":30001,
          "name":"Juego de Comedor",
          "image": "img/px/prod30001_1.jpg"
      },
      {
          "id":30002,
          "name":"Sof치",
          "image": "img/px/prod30002_1.jpg"
      },
      {
          "id":30003,
          "name":"Armario",
          "image": "img/px/prod50744_1.jpg"
      }
  ]
}
